simple_xsrf/__init__.py
simple_xsrf/exceptions.py
simple_xsrf/token.py
simple_xsrf-0.2.1.dist-info/WHEEL
simple_xsrf-0.2.1.dist-info/METADATA
simple_xsrf-0.2.1.dist-info/RECORD
