Metadata-Version: 2.1
Name: simple-xsrf
Version: 0.2.1
Summary: Simple package to protect against CSRF/XSRF attacks
Home-page: https://github.com/NWBY/simple-xsrf
License: MIT
Keywords: csrf,xsrf,security
Author: Sam Newby
Author-email: sam.newby19@gmail.com
Requires-Python: >=3.8,<4.0
Classifier: License :: OSI Approved :: MIT License
Classifier: Programming Language :: Python :: 3
Classifier: Programming Language :: Python :: 3.8
Classifier: Programming Language :: Python :: 3.9
Classifier: Programming Language :: Python :: 3.10
Classifier: Programming Language :: Python :: 3.11
Requires-Dist: cryptography (>=38.0.0,<38.1.0)
Project-URL: Repository, https://github.com/NWBY/simple-xsrf
